dynamic_form/__init__.py
dynamic_form/admin/__init__.py
dynamic_form/admin/field.py
dynamic_form/admin/field_type.py
dynamic_form/admin/form.py
dynamic_form/admin/form_submission.py
dynamic_form/api/__init__.py
dynamic_form/api/filters/__init__.py
dynamic_form/api/paginations/__init__.py
dynamic_form/api/paginations/limit_offset_pagination.py
dynamic_form/api/routers/__init__.py
dynamic_form/api/routers/main.py
dynamic_form/api/serializers/__init__.py
dynamic_form/api/serializers/field.py
dynamic_form/api/serializers/field_type.py
dynamic_form/api/serializers/form.py
dynamic_form/api/serializers/form_submission.py
dynamic_form/api/serializers/helper/get_serializer_cls.py
dynamic_form/api/serializers/user.py
dynamic_form/api/throttlings/__init__.py
dynamic_form/api/throttlings/role_base_throttle.py
dynamic_form/api/views/__init__.py
dynamic_form/api/views/base.py
dynamic_form/api/views/field.py
dynamic_form/api/views/field_type.py
dynamic_form/api/views/form.py
dynamic_form/api/views/form_submission.py
dynamic_form/apps.py
dynamic_form/constants/__init__.py
dynamic_form/constants/default_settings.py
dynamic_form/constants/types.py
dynamic_form/migrations/0001_initial.py
dynamic_form/migrations/0002_seed_field_types.py
dynamic_form/migrations/__init__.py
dynamic_form/mixins/__init__.py
dynamic_form/mixins/admin/__init__.py
dynamic_form/mixins/admin/permission.py
dynamic_form/mixins/api/__init__.py
dynamic_form/mixins/api/config_api_attrs.py
dynamic_form/mixins/api/control_api_methods.py
dynamic_form/models/__init__.py
dynamic_form/models/field.py
dynamic_form/models/field_type.py
dynamic_form/models/form.py
dynamic_form/models/form_submission.py
dynamic_form/settings/__init__.py
dynamic_form/settings/checks.py
dynamic_form/settings/conf.py
dynamic_form/tests/__init__.py
dynamic_form/tests/admin/__init__.py
dynamic_form/tests/admin/test_dynamic_form.py
dynamic_form/tests/admin/test_form_submission.py
dynamic_form/tests/api/__init__.py
dj_dynamic_form-1.0.0.dist-info/AUTHORS.md
dj_dynamic_form-1.0.0.dist-info/LICENSE
dj_dynamic_form-1.0.0.dist-info/METADATA
dj_dynamic_form-1.0.0.dist-info/WHEEL
dj_dynamic_form-1.0.0.dist-info/RECORD
